killprocess_cli/__init__.py
killprocess_cli-0.3.dist-info/METADATA
killprocess_cli-0.3.dist-info/WHEEL
killprocess_cli-0.3.dist-info/entry_points.txt
killprocess_cli-0.3.dist-info/top_level.txt
killprocess_cli-0.3.dist-info/RECORD
