Metadata-Version: 2.1
Name: killprocess-cli
Version: 0.3
Summary: A Python module to easily terminate Linux processes by name
Home-page: http://github.com/tushark39
Author: Tushar Pandey
Author-email: tushark39@gmail.com
License: MIT
Platform: UNKNOWN
Classifier: Programming Language :: Python :: 3
Classifier: License :: OSI Approved :: MIT License
Classifier: Operating System :: POSIX :: Linux
Classifier: Topic :: System :: Operating System Kernels :: Linux
